LogicHW0/__init__.py
LogicHW0/is_prime.py
LogicHW0/nth_prime.py
LogicHW0/prime_factorization.py
LogicHW0_CianeeS-0.0.222.dist-info/METADATA
LogicHW0_CianeeS-0.0.222.dist-info/WHEEL
LogicHW0_CianeeS-0.0.222.dist-info/top_level.txt
LogicHW0_CianeeS-0.0.222.dist-info/RECORD
