Metadata-Version: 2.1
Name: LogicHW0-CianeeS
Version: 0.0.222
Summary: HW0
Author: CianeeS
Author-email: <sumowalt@bc.edu>
Keywords: python
Classifier: License :: OSI Approved :: GNU General Public License (GPL)
Classifier: Development Status :: 1 - Planning
Classifier: Programming Language :: Python :: 3
Classifier: Operating System :: Unix
Classifier: Operating System :: MacOS :: MacOS X
Classifier: Operating System :: Microsoft :: Windows
